{"ref":"1 Chronicles 12","verses":{"1":[{"w":"Now these [were] the [men]","s":"H0428"},{"w":"who came","s":"H0935"},{"w":"to","s":"H0413"},{"w":"David","s":"H1732"},{"w":"at Ziklag,","s":"H6860"},{"w":"while","s":"H5750"},{"w":"he was still banished","s":"H6113"},{"w":"from the presence","s":"H6440"},{"w":"of Saul","s":"H7586"},{"w":"son","s":"H1121"},{"w":"of Kish","s":"H7027"},{"w":"they","s":"H1992"},{"w":"were among the mighty men","s":"H1368"},{"w":"who helped him","s":"H5826"},{"w":"in battle;","s":"H4421"}],"2":[{"w":"they were archers","s":"H5401"},{"w":"using both the right","s":"H3231"},{"w":"and left [hands]","s":"H8041"},{"w":"[to sling] stones","s":"H0068"},{"w":"and [shoot] arrows","s":"H2671"},{"w":"[and they were] Saul’s","s":"H7586"},{"w":"kinsmen","s":"H0251"},{"w":"from Benjamin):","s":"H1144"}],"3":[{"w":"Ahiezer","s":"H0295"},{"w":"their chief","s":"H7218"},{"w":"and Joash,","s":"H3101"},{"w":"[who were] the sons","s":"H1121"},{"w":"of Shemaah","s":"H8094"},{"w":"the Gibeathite;","s":"H1395"},{"w":"Jeziel","s":"H3149"},{"w":"and Pelet,","s":"H6404"},{"w":"the sons","s":"H1121"},{"w":"of Azmaveth;","s":"H5820"},{"w":"Beracah;","s":"H1294"},{"w":"Jehu","s":"H3058"},{"w":"the Anathothite;","s":"H6069"}],"4":[{"w":"Ishmaiah","s":"H3460"},{"w":"the Gibeonite,","s":"H1393"},{"w":"a mighty man","s":"H1368"},{"w":"among the Thirty","s":"H7970"},{"w":"and a leader over","s":"H5921"},{"w":"the Thirty;","s":"H7970"},{"w":"Jeremiah,","s":"H3414"},{"w":"Jahaziel,","s":"H3166"},{"w":"Johanan,","s":"H3076"},{"w":"and Jozabad","s":"H3107"},{"w":"the Gederathite;","s":"H1452"}],"5":[{"w":"Eluzai,","s":"H0498"},{"w":"Jerimoth,","s":"H3406"},{"w":"Bealiah,","s":"H1183"},{"w":"Shemariah,","s":"H8114"},{"w":"and Shephatiah","s":"H8203"},{"w":"the Haruphite;","s":"H2741"}],"6":[{"w":"Elkanah,","s":"H0511"},{"w":"Isshiah,","s":"H3449"},{"w":"Azarel,","s":"H5832"},{"w":"Joezer,","s":"H3134"},{"w":"and Jashobeam,","s":"H3434"},{"w":"[who were] Korahites;","s":"H7145"}],"7":[{"w":"and Joelah","s":"H3132"},{"w":"and Zebadiah,","s":"H2069"},{"w":"the sons","s":"H1121"},{"w":"of Jeroham","s":"H3395"},{"w":"from","s":"H4480"},{"w":"Gedor.","s":"H1446"}],"8":[{"w":"Some","s":"H4480"},{"w":"Gadites","s":"H1425"},{"w":"defected","s":"H0914"},{"w":"to","s":"H0413"},{"w":"David","s":"H1732"},{"w":"at his stronghold","s":"H4679"},{"w":"in the wilderness.","s":"H4057"},{"w":"They were mighty","s":"H1368"},{"w":"men","s":"H0376"},{"w":"of valor,","s":"H2428"},{"w":"trained","s":"H6635"},{"w":"for battle,","s":"H4421"},{"w":"experts","s":"H6186"},{"w":"with the shield","s":"H6793"},{"w":"and spear,","s":"H7420"},{"w":"whose faces [were like]","s":"H6440"},{"w":"the faces","s":"H6440"},{"w":"of lions","s":"H0738"},{"w":"and who were as swift","s":"H4116"},{"w":"as gazelles","s":"H6643"},{"w":"on","s":"H5921"},{"w":"the mountains:","s":"H2022"}],"9":[{"w":"Ezer","s":"H5829"},{"w":"the chief,","s":"H7218"},{"w":"Obadiah","s":"H5662"},{"w":"the second [in command],","s":"H8145"},{"w":"Eliab","s":"H0446"},{"w":"the third,","s":"H7992"}],"10":[{"w":"Mishmannah","s":"H4925"},{"w":"the fourth,","s":"H7243"},{"w":"Jeremiah","s":"H3414"},{"w":"the fifth,","s":"H2549"}],"11":[{"w":"Attai","s":"H6262"},{"w":"the sixth,","s":"H8345"},{"w":"Eliel","s":"H0447"},{"w":"the seventh,","s":"H7637"}],"12":[{"w":"Johanan","s":"H3076"},{"w":"the eighth,","s":"H8066"},{"w":"Elzabad","s":"H0443"},{"w":"the ninth,","s":"H8671"}],"13":[{"w":"Jeremiah","s":"H3414"},{"w":"the tenth,","s":"H6224"},{"w":"and Machbanai","s":"H4344"},{"w":"the eleventh","s":"H6249"}],"14":[{"w":"These","s":"H0428"},{"w":"Gadites","s":"H1121"},{"w":"were army","s":"H6635"},{"w":"commanders,","s":"H7218"},{"w":"the least [of whom]","s":"H6996"},{"w":"was a match for a hundred,","s":"H3967"},{"w":"and the greatest","s":"H1419"},{"w":"for a thousand.","s":"H0505"}],"15":[{"w":"These","s":"H0428"},{"w":"are","s":"H1992"},{"w":"the ones who","s":"H0834"},{"w":"crossed","s":"H5674"},{"w":"the Jordan","s":"H3383"},{"w":"in the first","s":"H7223"},{"w":"month","s":"H2320"},{"w":"when it was overflowing","s":"H4390"},{"w":"all","s":"H3605"},{"w":"its banks,","s":"H1428"},{"w":"and they put to flight","s":"H1272"},{"w":"all [those]","s":"H3605"},{"w":"in the valleys,","s":"H6010"},{"w":"[both] to the east","s":"H4217"},{"w":"and to the west.","s":"H4628"}],"16":[{"w":"Other Benjamites","s":"H1121"},{"w":"and some men from Judah","s":"H3063"},{"w":"also came","s":"H0935"},{"w":"to David","s":"H1732"},{"w":"in his stronghold.","s":"H4679"}],"17":[{"w":"And David","s":"H3318"},{"w":"went out","s":"H1732"},{"w":"to meet them,","s":"H6440"},{"w":"saying","s":"H0559"},{"w":"If","s":"H0518"},{"w":"you have come","s":"H0935"},{"w":"to me","s":"H0413"},{"w":"in peace","s":"H7965"},{"w":"to help me,","s":"H5826"},{"w":"my","s":""},{"w":"heart","s":"H3824"},{"w":"will be","s":"H1961"},{"w":"united","s":"H3162"},{"w":"with you;","s":"H5921"},{"w":"but if","s":"H0518"},{"w":"you have come to betray me","s":"H7411"},{"w":"to my enemies","s":"H6862"},{"w":"when my hands","s":"H3709"},{"w":"are free","s":"H3808"},{"w":"of violence,","s":"H2555"},{"w":"may the God","s":"H0430"},{"w":"of our fathers","s":"H0001"},{"w":"see [it]","s":"H7200"},{"w":"and judge you.","s":"H3198"}],"18":[{"w":"Then the Spirit","s":"H7307"},{"w":"came upon","s":"H3847"},{"w":"Amasai,","s":"H6022"},{"w":"the chief","s":"H7218"},{"w":"of the Thirty, and he said:","s":"H7970"},{"w":"We are yours,","s":""},{"w":"O David!","s":"H1732"},{"w":"We are with you,","s":"H5973"},{"w":"O son","s":"H1121"},{"w":"of Jesse!","s":"H3448"},{"w":"Peace,","s":"H7965"},{"w":"peace","s":"H7965"},{"w":"to you,","s":""},{"w":"and peace","s":"H7965"},{"w":"to your helpers,","s":"H5826"},{"w":"for","s":"H3588"},{"w":"your God","s":"H0430"},{"w":"helps you.","s":"H5826"},{"w":"So David","s":"H1732"},{"w":"received them","s":"H6901"},{"w":"and made them","s":"H5414"},{"w":"leaders","s":"H7218"},{"w":"of his troops.","s":"H1416"}],"19":[{"w":"Some from","s":"H5307"},{"w":"Manasseh","s":"H4519"},{"w":"defected","s":"H5921"},{"w":"to David","s":"H1732"},{"w":"when he went","s":"H0935"},{"w":"with","s":"H5973"},{"w":"the Philistines","s":"H6430"},{"w":"to fight","s":"H5921"},{"w":"against","s":"H7586"},{"w":"Saul.","s":"H4421"},{"w":"They did not","s":"H3808"},{"w":"help the Philistines","s":"H5826"},{"w":"because","s":"H3588"},{"w":"the Philistine","s":"H6430"},{"w":"rulers","s":"H5633"},{"w":"consulted","s":"H6098"},{"w":"and sent David away,","s":"H7971"},{"w":"saying,","s":"H0559"},{"w":"It will cost us our heads","s":"H7218"},{"w":"if he defects","s":"H5307"},{"w":"to","s":"H0413"},{"w":"his master","s":"H0113"},{"w":"Saul.","s":"H7586"}],"20":[{"w":"When David went","s":"H1980"},{"w":"to","s":"H0413"},{"w":"Ziklag,","s":"H6860"},{"w":"these men of Manasseh","s":"H4519"},{"w":"defected","s":"H5307"},{"w":"to him:","s":"H5921"},{"w":"Adnah,","s":"H5734"},{"w":"Jozabad,","s":"H3107"},{"w":"Jediael,","s":"H3043"},{"w":"Michael,","s":"H4317"},{"w":"Jozabad,","s":"H3107"},{"w":"Elihu,","s":"H0453"},{"w":"and Zillethai,","s":"H6769"},{"w":"chiefs","s":"H7218"},{"w":"of thousands","s":"H0505"},{"w":"in Manasseh.","s":"H4519"}],"21":[{"w":"They","s":"H1992"},{"w":"helped","s":"H5826"},{"w":"David","s":"H1732"},{"w":"against","s":"H5921"},{"w":"the raiders,","s":"H1416"},{"w":"for","s":"H3588"},{"w":"they were","s":"H1961"},{"w":"all","s":"H3605"},{"w":"mighty men","s":"H1368"},{"w":"of valor","s":"H2428"},{"w":"and commanders","s":"H8269"},{"w":"in the army.","s":"H6635"}],"22":[{"w":"For","s":"H3588"},{"w":"at [that] time","s":"H6256"},{"w":"men came","s":"H0935"},{"w":"to","s":"H5921"},{"w":"David","s":"H1732"},{"w":"day","s":"H3117"},{"w":"after day","s":"H3117"},{"w":"to help him,","s":"H5826"},{"w":"until","s":"H5704"},{"w":"he had a great","s":"H1419"},{"w":"army,","s":"H4264"},{"w":"like the army","s":"H4264"},{"w":"of God.","s":"H0430"}],"23":[{"w":"Now these [are]","s":"H0428"},{"w":"the numbers","s":"H4557"},{"w":"of men","s":"H7218"},{"w":"armed","s":"H2502"},{"w":"for battle","s":"H6635"},{"w":"who came","s":"H0935"},{"w":"to","s":"H5921"},{"w":"David","s":"H1732"},{"w":"at Hebron","s":"H2275"},{"w":"to turn Saul’s","s":"H7586"},{"w":"kingdom","s":"H4438"},{"w":"over","s":"H5437"},{"w":"to him,","s":"H0413"},{"w":"in accordance with the word of","s":"H6310"},{"w":"the LORD:","s":"H3068"}],"24":[{"w":"From Judah","s":"H1121"},{"w":"6,800","s":"H8337"},{"w":"armed","s":"H2502"},{"w":"troops","s":"H6635"},{"w":"bearing","s":"H5375"},{"w":"shields","s":"H6793"},{"w":"and spears.","s":"H7420"}],"25":[{"w":"From","s":"H4480"},{"w":"Simeon","s":"H1121"},{"w":"7,100","s":"H7651"},{"w":"mighty men","s":"H1368"},{"w":"of valor,","s":"H2428"},{"w":"ready for battle.","s":"H6635"}],"26":[{"w":"From","s":"H4480"},{"w":"Levi","s":"H1121"},{"w":"4,600","s":"H0702"}],"27":[{"w":"including Jehoiada,","s":"H3077"},{"w":"leader","s":"H5057"},{"w":"of the house of Aaron,","s":"H0175"},{"w":"with","s":"H5973"},{"w":"3,700","s":"H7969"},{"w":"men,","s":"H3967"}],"28":[{"w":"and Zadok,","s":"H6659"},{"w":"a mighty","s":"H1368"},{"w":"young man","s":"H5288"},{"w":"of valor,","s":"H2428"},{"w":"with 22","s":"H6242"},{"w":"commanders","s":"H8269"},{"w":"from his own family","s":"H0001"}],"29":[{"w":"From","s":"H4480"},{"w":"Benjamin","s":"H1121"},{"w":"the kinsmen","s":"H0251"},{"w":"of Saul:","s":"H7586"},{"w":"3,000 {},","s":"H7969"},{"w":"most of whom","s":"H4768"},{"w":"had remained","s":"H8104"},{"w":"loyal to","s":"H4931"},{"w":"the house","s":"H1004"},{"w":"of Saul","s":"H7586"},{"w":"up to","s":"H5704"},{"w":"that time.","s":"H2008"}],"30":[{"w":"From","s":"H4480"},{"w":"Ephraim","s":"H1121"},{"w":"20,800","s":"H6242"},{"w":"mighty men","s":"H1368"},{"w":"of valor,","s":"H2428"},{"w":"famous","s":"H8034"},{"w":"among their own clans","s":"H1004"}],"31":[{"w":"From the half-tribe","s":"H2677"},{"w":"of Manasseh:","s":"H4519"},{"w":"18,000 {}","s":"H8083"},{"w":"designated","s":"H5344"},{"w":"by name","s":"H8034"},{"w":"to come","s":"H0935"},{"w":"and make David","s":"H1732"},{"w":"king.","s":"H4427"}],"32":[{"w":"From Issachar","s":"H1121"},{"w":"[men] who understood","s":"H3045"},{"w":"the times","s":"H6256"},{"w":"and knew","s":"H3045"},{"w":"what","s":"H4100"},{"w":"Israel","s":"H3478"},{"w":"should do:","s":"H6213"},{"w":"200","s":"H3967"},{"w":"chiefs","s":"H7218"},{"w":"with all","s":"H3605"},{"w":"their kinsmen","s":"H0251"},{"w":"at","s":"H5921"},{"w":"their command.","s":"H6310"}],"33":[{"w":"From Zebulun:","s":"H2074"},{"w":"50,000 {}","s":"H2572"},{"w":"fit for service","s":"H3318"},{"w":"trained","s":"H6186"},{"w":"for battle","s":"H4421"},{"w":"with all kinds","s":"H3605"},{"w":"of weapons","s":"H3627"},{"w":"of war","s":"H4421"},{"w":"who with one purpose","s":"H3820"},{"w":"were devoted [to David].","s":"H5737"}],"34":[{"w":"From Naphtali:","s":"H5321"},{"w":"1,000 {}","s":"H8269"},{"w":"commanders,","s":"H0505"},{"w":"accompanied","s":"H5973"},{"w":"by 37,000","s":"H7970"},{"w":"men with shield","s":"H6793"},{"w":"and spear.","s":"H2595"}],"35":[{"w":"From","s":"H4480"},{"w":"Dan:","s":"H1839"},{"w":"28,600 {}","s":"H6242"},{"w":"prepared","s":"H6186"},{"w":"for battle.","s":"H4421"}],"36":[{"w":"From Asher:","s":"H0836"},{"w":"40,000 {}","s":"H0705"},{"w":"fit for service","s":"H3318"},{"w":"prepared","s":"H6186"},{"w":"for battle.","s":"H4421"}],"37":[{"w":"And from east","s":"H5676"},{"w":"of the Jordan,","s":"H3383"},{"w":"from","s":"H4480"},{"w":"Reuben,","s":"H7206"},{"w":"Gad,","s":"H1425"},{"w":"and","s":"H2677"},{"w":"the half-tribe","s":"H7626"},{"w":"of Manasseh [there]:","s":"H4519"},{"w":"120,000 {}","s":"H3967"},{"w":"[armed] with every [kind]","s":"H3605"},{"w":"of weapon","s":"H3627"},{"w":"of war.","s":"H4421"}],"38":[{"w":"All","s":"H3605"},{"w":"these","s":"H0428"},{"w":"men","s":"H0376"},{"w":"of war,","s":"H4421"},{"w":"arrayed","s":"H5737"},{"w":"for battle,","s":"H4634"},{"w":"came","s":"H0935"},{"w":"to Hebron","s":"H2275"},{"w":"fully","s":"H8003"},{"w":"determined","s":"H3824"},{"w":"to make David","s":"H1732"},{"w":"king","s":"H4427"},{"w":"over","s":"H5921"},{"w":"all","s":"H3605"},{"w":"Israel.","s":"H3478"},{"w":"And","s":"H1571"},{"w":"all","s":"H3605"},{"w":"the rest","s":"H7611"},{"w":"of the Israelites","s":"H3478"},{"w":"[were] of one","s":"H0259"},{"w":"mind","s":"H3820"},{"w":"to make David","s":"H1732"},{"w":"king.","s":"H4427"}],"39":[{"w":"They spent","s":"H1961"},{"w":"three","s":"H7969"},{"w":"days","s":"H3117"},{"w":"there","s":"H8033"},{"w":"eating","s":"H0398"},{"w":"and drinking","s":"H8354"},{"w":"with","s":"H5973"},{"w":"David,","s":"H1732"},{"w":"for their","s":"H3588"},{"w":"relatives","s":""},{"w":"had provided for them.","s":"H3559"}],"40":[{"w":"And their neighbors","s":"H1571"},{"w":"from as far away as","s":"H0413"},{"w":"Issachar,","s":"H3485"},{"w":"Zebulun,","s":"H2074"},{"w":"and Naphtali","s":"H5321"},{"w":"came bringing","s":"H0935"},{"w":"food","s":"H3899"},{"w":"on donkeys,","s":"H2543"},{"w":"camels,","s":"H1581"},{"w":"mules,","s":"H6505"},{"w":"and oxen—","s":"H1241"},{"w":"abundant supplies","s":"H3978"},{"w":"of flour,","s":"H7058"},{"w":"fig cakes","s":"H1690"},{"w":"and","s":"H6778"},{"w":"raisin cakes,","s":"H3196"},{"w":"wine","s":"H8081"},{"w":"and oil,","s":"H1241"},{"w":"oxen","s":"H6629"},{"w":"and sheep.","s":"H7230"},{"w":"Indeed,","s":"H3588"},{"w":"there was joy","s":"H8057"},{"w":"in Israel.","s":"H3478"}]}}