{"ref":"Ephesians 5","verses":{"1":[{"w":"Be","s":"G1096"},{"w":"imitators","s":"G3402"},{"w":"of God,","s":"G2316"},{"w":"therefore,","s":"G3767"},{"w":"as","s":"G5613"},{"w":"beloved","s":"G0027"},{"w":"children,","s":"G5043"}],"2":[{"w":"and","s":"G2532"},{"w":"walk","s":"G4043"},{"w":"in","s":"G1722"},{"w":"love,","s":"G0026"},{"w":"just as","s":"G2531"},{"w":"Christ","s":"G5547"},{"w":"loved","s":"G0025"},{"w":"us","s":"G1473"},{"w":"and","s":"G2532"},{"w":"gave Himself up","s":"G3860"},{"w":"for","s":"G5228"},{"w":"us","s":"G1473"},{"w":"as","s":"G1519"},{"w":"vvv","s":"G3744"},{"w":"a fragrant","s":"G2175"},{"w":"sacrificial","s":"G2378"},{"w":"offering","s":"G4376"},{"w":"to God.","s":"G2316"}],"3":[{"w":"But","s":"G1161"},{"w":"among","s":"G1722"},{"w":"you,","s":"G4771"},{"w":"as","s":"G2531"},{"w":"is proper","s":"G4241"},{"w":"among the saints,","s":"G0040"},{"w":"vvv","s":"G3366"},{"w":"there must not be even a hint","s":"G3687"},{"w":"of sexual immorality,","s":"G4202"},{"w":"[or]","s":"G2532"},{"w":"of any kind","s":"G3956"},{"w":"of impurity,","s":"G0167"},{"w":"or","s":"G2228"},{"w":"of greed.","s":"G4124"}],"4":[{"w":"[Nor should there be]","s":"G2532"},{"w":"obscenity,","s":"G0151"},{"w":"foolish talk,","s":"G3473"},{"w":"or","s":"G2228"},{"w":"crude joking,","s":"G2160"},{"w":"which","s":"G3739"},{"w":"vvv","s":"G3756"},{"w":"are out of character,","s":"G0433"},{"w":"but","s":"G0235"},{"w":"rather","s":"G3123"},{"w":"thanksgiving.","s":"G2169"}],"5":[{"w":"For","s":"G1063"},{"w":"of this","s":"G3778"},{"w":"vvv","s":"G1492"},{"w":"you can be sure","s":"G1097"},{"w":"[No]","s":"G3956"},{"w":"immoral,","s":"G4205"},{"w":"impure,","s":"G0169"},{"w":"or","s":"G2228"},{"w":"greedy person","s":"G4123"},{"w":"(that","s":"G3739"},{"w":"is,","s":"G1510"},{"w":"an idolater)","s":"G1496"},{"w":"has","s":"G2192"},{"w":"[any]","s":"G3756"},{"w":"inheritance","s":"G2817"},{"w":"in","s":"G1722"},{"w":"the","s":"G3588"},{"w":"kingdom","s":"G0932"},{"w":"of Christ","s":"G5547"},{"w":"and","s":"G2532"},{"w":"of God.","s":"G2316"}],"6":[{"w":"{Let} no one","s":"G3367"},{"w":"deceive","s":"G0538"},{"w":"you","s":"G4771"},{"w":"with empty","s":"G2756"},{"w":"words,","s":"G3056"},{"w":"for","s":"G1063"},{"w":"because of","s":"G1223"},{"w":"such things","s":"G3778"},{"w":"the","s":"G3588"},{"w":"wrath","s":"G3709"},{"w":"of God","s":"G2316"},{"w":"is coming","s":"G2064"},{"w":"on","s":"G1909"},{"w":"the","s":"G3588"},{"w":"sons","s":"G5207"},{"w":"of disobedience.","s":"G0543"}],"7":[{"w":"Therefore","s":"G3767"},{"w":"{do} not","s":"G3361"},{"w":"be","s":"G1096"},{"w":"partakers","s":"G4830"},{"w":"with them.","s":"G0846"}],"8":[{"w":"For","s":"G1063"},{"w":"you were","s":"G1510"},{"w":"once","s":"G4218"},{"w":"darkness,","s":"G4655"},{"w":"but","s":"G1161"},{"w":"now","s":"G3568"},{"w":"[you are] light","s":"G5457"},{"w":"in","s":"G1722"},{"w":"[the] Lord.","s":"G2962"},{"w":"Walk","s":"G4043"},{"w":"as","s":"G5613"},{"w":"children","s":"G5043"},{"w":"of light,","s":"G5457"}],"9":[{"w":"for","s":"G1063"},{"w":"the","s":"G3588"},{"w":"fruit","s":"G2590"},{"w":"of the","s":"G3588"},{"w":"light [consists]","s":"G5457"},{"w":"in","s":"G1722"},{"w":"all","s":"G3956"},{"w":"goodness,","s":"G0019"},{"w":"righteousness,","s":"G1343"},{"w":"and","s":"G2532"},{"w":"truth.","s":"G0225"}],"10":[{"w":"Test and prove","s":"G1381"},{"w":"what","s":"G5101"},{"w":"vvv","s":"G1510"},{"w":"pleases","s":"G2101"},{"w":"the","s":"G3588"},{"w":"Lord.","s":"G2962"}],"11":[{"w":"vvv","s":"G3361"},{"w":"Have no fellowship with","s":"G4790"},{"w":"the","s":"G3588"},{"w":"fruitless","s":"G0175"},{"w":"deeds","s":"G2041"},{"w":"of darkness,","s":"G4655"},{"w":"but","s":"G1161"},{"w":"rather","s":"G3123"},{"w":"expose [them].","s":"G1651"}],"12":[{"w":"For","s":"G1063"},{"w":"it is","s":"G1510"},{"w":"shameful","s":"G0150"},{"w":"even","s":"G2532"},{"w":"to mention","s":"G3004"},{"w":"what","s":"G3588"},{"w":"[the disobedient] do","s":"G1096"},{"w":"in secret.","s":"G2931"}],"13":[{"w":"But","s":"G1161"},{"w":"everything","s":"G3956"},{"w":"exposed","s":"G1651"},{"w":"by","s":"G5259"},{"w":"the","s":"G3588"},{"w":"light","s":"G5457"},{"w":"becomes visible,","s":"G5319"},{"w":"for","s":"G1063"},{"w":"everything","s":"G3956"},{"w":"that","s":"G3588"},{"w":"is illuminated","s":"G5319"},{"w":"becomes","s":"G1510"},{"w":"a light [itself].","s":"G5457"}],"14":[{"w":"So","s":"G1352"},{"w":"it is said:","s":"G3004"},{"w":"Wake up,","s":"G1453"},{"w":"O","s":"G3588"},{"w":"sleeper,","s":"G2518"},{"w":"rise up","s":"G0450"},{"w":"from","s":"G1537"},{"w":"the","s":"G3588"},{"w":"dead,","s":"G3498"},{"w":"and","s":"G2532"},{"w":"Christ","s":"G5547"},{"w":"will shine on","s":"G2017"},{"w":"you.","s":"G4771"}],"15":[{"w":"Pay careful","s":"G0199"},{"w":"attention,","s":"G0991"},{"w":"then,","s":"G3767"},{"w":"to how","s":"G4459"},{"w":"you walk,","s":"G4043"},{"w":"not","s":"G3361"},{"w":"as","s":"G5613"},{"w":"unwise","s":"G0781"},{"w":"but","s":"G0235"},{"w":"as","s":"G5613"},{"w":"wise,","s":"G4680"}],"16":[{"w":"redeeming","s":"G1805"},{"w":"the","s":"G3588"},{"w":"time,","s":"G2540"},{"w":"because","s":"G3754"},{"w":"the","s":"G3588"},{"w":"days","s":"G2250"},{"w":"are","s":"G1510"},{"w":"evil.","s":"G4190"}],"17":[{"w":"Therefore","s":"G1223"},{"w":"{do} not","s":"G3361"},{"w":"be","s":"G1096"},{"w":"foolish,","s":"G0878"},{"w":"but","s":"G0235"},{"w":"understand","s":"G4920"},{"w":"what","s":"G5101"},{"w":"the","s":"G3588"},{"w":"Lord’s","s":"G2962"},{"w":"will [is].","s":"G2307"}],"18":[{"w":"{Do} not","s":"G3361"},{"w":"get drunk","s":"G3182"},{"w":"on wine,","s":"G3631"},{"w":"which","s":"G3739"},{"w":"leads to","s":"G1510"},{"w":"reckless indiscretion.","s":"G0810"},{"w":"Instead,","s":"G0235"},{"w":"be filled","s":"G4137"},{"w":"with","s":"G1722"},{"w":"[the] Spirit.","s":"G4151"}],"19":[{"w":"Speak","s":"G2980"},{"w":"to one another","s":"G1438"},{"w":"with","s":"G1722"},{"w":"psalms,","s":"G5568"},{"w":"hymns,","s":"G5215"},{"w":"and","s":"G2532"},{"w":"spiritual","s":"G4152"},{"w":"songs.","s":"G5603"},{"w":"Sing","s":"G0103"},{"w":"and","s":"G2532"},{"w":"make music","s":"G5567"},{"w":"in","s":"G3588"},{"w":"your","s":"G4771"},{"w":"hearts","s":"G2588"},{"w":"to the","s":"G3588"},{"w":"Lord,","s":"G2962"}],"20":[{"w":"always","s":"G3842"},{"w":"giving thanks","s":"G2168"},{"w":"to","s":"G3588"},{"w":"God","s":"G2316"},{"w":"[the] Father","s":"G3962"},{"w":"for","s":"G5228"},{"w":"everything","s":"G3956"},{"w":"in","s":"G1722"},{"w":"[the] name","s":"G3686"},{"w":"of our","s":"G1473"},{"w":"Lord","s":"G2962"},{"w":"Jesus","s":"G2424"},{"w":"Christ.","s":"G5547"}],"21":[{"w":"Submit","s":"G5293"},{"w":"to one another","s":"G0240"},{"w":"out of","s":"G1722"},{"w":"reverence","s":"G5401"},{"w":"for Christ.","s":"G5547"}],"22":[{"w":"Wives,","s":"G1135"},{"w":"[submit] to","s":"G3588"},{"w":"your","s":"G2398"},{"w":"husbands","s":"G0435"},{"w":"as","s":"G5613"},{"w":"to the","s":"G3588"},{"w":"Lord.","s":"G2962"}],"23":[{"w":"For","s":"G3754"},{"w":"[the] husband","s":"G0435"},{"w":"is","s":"G1510"},{"w":"[the] head","s":"G2776"},{"w":"of the","s":"G3588"},{"w":"wife","s":"G1135"},{"w":"as","s":"G5613"},{"w":"Christ","s":"G5547"},{"w":"[is the] head","s":"G2776"},{"w":"of the","s":"G3588"},{"w":"church,","s":"G1577"},{"w":"[His]","s":"G3588"},{"w":"body,","s":"G4983"},{"w":"[of which] He","s":"G0846"},{"w":"[is the] Savior.","s":"G4990"}],"24":[{"w":"Now","s":"G0235"},{"w":"as","s":"G5613"},{"w":"the","s":"G3588"},{"w":"church","s":"G1577"},{"w":"submits","s":"G5293"},{"w":"to Christ,","s":"G5547"},{"w":"so","s":"G3779"},{"w":"also","s":"G2532"},{"w":"wives [should submit]","s":"G1135"},{"w":"to their","s":"G3588"},{"w":"husbands","s":"G0435"},{"w":"in","s":"G1722"},{"w":"everything.","s":"G3956"}],"25":[{"w":"Husbands,","s":"G0435"},{"w":"love","s":"G0025"},{"w":"[your]","s":"G3588"},{"w":"wives,","s":"G1135"},{"w":"just","s":"G2532"},{"w":"as","s":"G2531"},{"w":"Christ","s":"G5547"},{"w":"loved","s":"G0025"},{"w":"the","s":"G3588"},{"w":"church","s":"G1577"},{"w":"and","s":"G2532"},{"w":"gave Himself up","s":"G3860"},{"w":"for","s":"G5228"},{"w":"her","s":"G0846"}],"26":[{"w":"to","s":"G2443"},{"w":"sanctify","s":"G0037"},{"w":"her,","s":"G0846"},{"w":"cleansing [her]","s":"G2511"},{"w":"by the","s":"G3588"},{"w":"washing","s":"G3067"},{"w":"with water","s":"G5204"},{"w":"through","s":"G1722"},{"w":"[the] word,","s":"G4487"}],"27":[{"w":"[and] to","s":"G2443"},{"w":"present","s":"G3936"},{"w":"her","s":"G0846"},{"w":"to Himself","s":"G1438"},{"w":"as a glorious","s":"G1741"},{"w":"church,","s":"G1577"},{"w":"vvv","s":"G3361"},{"w":"without","s":"G2192"},{"w":"stain","s":"G4696"},{"w":"or","s":"G2228"},{"w":"wrinkle","s":"G4512"},{"w":"or","s":"G2228"},{"w":"any","s":"G5100"},{"w":"such [blemish],","s":"G5108"},{"w":"but","s":"G0235"},{"w":"holy","s":"G0040"},{"w":"and","s":"G2532"},{"w":"blameless.","s":"G0299"}],"28":[{"w":"In the same way","s":"G3779"},{"w":"husbands","s":"G0435"},{"w":"ought","s":"G3784"},{"w":"to love","s":"G0025"},{"w":"their","s":"G1438"},{"w":"wives","s":"G1135"},{"w":"as","s":"G5613"},{"w":"their own","s":"G1438"},{"w":"bodies.","s":"G4983"},{"w":"He","s":"G3588"},{"w":"who loves","s":"G0025"},{"w":"his","s":"G1438"},{"w":"wife","s":"G1135"},{"w":"loves","s":"G0025"},{"w":"himself.","s":"G1438"}],"29":[{"w":"Indeed,","s":"G1063"},{"w":"no one","s":"G3762"},{"w":"ever","s":"G4218"},{"w":"hated","s":"G3404"},{"w":"his","s":"G1438"},{"w":"[own]","s":"G3588"},{"w":"body,","s":"G4561"},{"w":"but","s":"G0235"},{"w":"he nourishes","s":"G1625"},{"w":"and","s":"G2532"},{"w":"cherishes","s":"G2282"},{"w":"it,","s":"G0846"},{"w":"just as","s":"G2531"},{"w":"Christ","s":"G5547"},{"w":"[does]","s":"G2532"},{"w":"the","s":"G3588"},{"w":"church.","s":"G1577"}],"30":[{"w":"For","s":"G3754"},{"w":"we are","s":"G1510"},{"w":"members","s":"G3196"},{"w":"of","s":"G3588"},{"w":"His","s":"G0846"},{"w":"body.","s":"G4983"}],"31":[{"w":"For this reason","s":"G0473"},{"w":"a man","s":"G0444"},{"w":"will leave","s":"G2641"},{"w":"his","s":"G3588"},{"w":"father","s":"G3962"},{"w":"and","s":"G2532"},{"w":"mother","s":"G3384"},{"w":"and","s":"G2532"},{"w":"be united","s":"G4347"},{"w":"to","s":"G4314"},{"w":"his","s":"G0846"},{"w":"wife,","s":"G1135"},{"w":"and","s":"G2532"},{"w":"the","s":"G3588"},{"w":"two","s":"G1417"},{"w":"will become","s":"G1510"},{"w":"one","s":"G1520"},{"w":"flesh.”","s":"G4561"}],"32":[{"w":"This","s":"G3778"},{"w":"mystery","s":"G3466"},{"w":"is","s":"G1510"},{"w":"profound,","s":"G3173"},{"w":"but","s":"G1161"},{"w":"I","s":"G1473"},{"w":"am speaking","s":"G3004"},{"w":"about","s":"G1519"},{"w":"Christ","s":"G5547"},{"w":"and","s":"G2532"},{"w":"the","s":"G3588"},{"w":"church.","s":"G1577"}],"33":[{"w":"Nevertheless,","s":"G4133"},{"w":"each one","s":"G1538"},{"w":"of you","s":"G4771"},{"w":"also","s":"G2532"},{"w":"must love","s":"G0025"},{"w":"his","s":"G1438"},{"w":"wife","s":"G1135"},{"w":"as [he loves]","s":"G5613"},{"w":"himself,","s":"G1438"},{"w":"and","s":"G1161"},{"w":"the","s":"G3588"},{"w":"wife","s":"G1135"},{"w":"must respect","s":"G5399"},{"w":"[her]","s":"G3588"},{"w":"husband.","s":"G0435"}]}}