{"ref":"Joel 1","verses":{"1":[{"w":"[This is] the word","s":"H1697"},{"w":"of the LORD","s":"H3068"},{"w":"that","s":"H0834"},{"w":"came","s":"H1961"},{"w":"to","s":"H0413"},{"w":"Joel","s":"H3100"},{"w":"son","s":"H1121"},{"w":"of Pethuel:","s":"H6602"}],"2":[{"w":"Hear","s":"H8085"},{"w":"this,","s":"H2063"},{"w":"O elders;","s":"H2205"},{"w":"and give ear,","s":"H0238"},{"w":"all","s":"H3605"},{"w":"who dwell","s":"H3427"},{"w":"in the land.","s":"H0776"},{"w":"Has anything like this","s":"H2063"},{"w":"ever happened","s":"H1961"},{"w":"in your days","s":"H3117"},{"w":"or","s":"H0518"},{"w":"in the days","s":"H3117"},{"w":"of your fathers?","s":"H0001"}],"3":[{"w":"Tell","s":"H5608"},{"w":"it","s":"H5921"},{"w":"to your children;","s":"H1121"},{"w":"let your children","s":"H1121"},{"w":"tell it to their children,","s":"H1121"},{"w":"and their children","s":"H1121"},{"w":"to the next","s":"H0312"},{"w":"generation.","s":"H1755"}],"4":[{"w":"What the devouring locust","s":"H1501"},{"w":"has left,","s":"H3499"},{"w":"the swarming locust","s":"H0697"},{"w":"has eaten;","s":"H0398"},{"w":"what the swarming locust","s":"H0697"},{"w":"has left,","s":"H3499"},{"w":"the young locust","s":"H3218"},{"w":"has eaten;","s":"H0398"},{"w":"and what the young locust","s":"H3218"},{"w":"has left,","s":"H3499"},{"w":"the destroying locust","s":"H2625"},{"w":"has eaten.","s":"H0398"}],"5":[{"w":"Wake up,","s":"H6974"},{"w":"you drunkards,","s":"H7910"},{"w":"and weep;","s":"H1058"},{"w":"wail,","s":"H3213"},{"w":"all","s":"H3605"},{"w":"you drinkers","s":"H8354"},{"w":"of wine,","s":"H3196"},{"w":"because of","s":"H5921"},{"w":"the sweet wine,","s":"H6071"},{"w":"for","s":"H3588"},{"w":"it has been cut off","s":"H3772"},{"w":"from your mouth.","s":"H6310"}],"6":[{"w":"For","s":"H3588"},{"w":"a nation","s":"H1471"},{"w":"has invaded","s":"H5927"},{"w":"My land,","s":"H0776"},{"w":"powerful","s":"H6099"},{"w":"and without","s":"H0369"},{"w":"number;","s":"H4557"},{"w":"its teeth","s":"H8127"},{"w":"[are] the teeth","s":"H8127"},{"w":"of a lion,","s":"H0738"},{"w":"and its fangs [are the fangs]","s":"H4973"},{"w":"of a lioness","s":"H3833"}],"7":[{"w":"It has laid","s":"H7760"},{"w":"waste","s":"H8047"},{"w":"My grapevine","s":"H1612"},{"w":"and splintered","s":"H7111"},{"w":"My fig tree.","s":"H8384"},{"w":"It has stripped off the bark","s":"H2834"},{"w":"and thrown it away;","s":"H7993"},{"w":"the branches","s":"H8299"},{"w":"have turned white.","s":"H3835"}],"8":[{"w":"Wail","s":"H0421"},{"w":"like a virgin","s":"H1330"},{"w":"dressed","s":"H2296"},{"w":"in sackcloth,","s":"H8242"},{"w":"grieving for","s":"H5921"},{"w":"the husband","s":"H1167"},{"w":"of her youth.","s":"H5271"}],"9":[{"w":"Grain and drink offerings","s":"H4503"},{"w":"have been cut off","s":"H3772"},{"w":"from the house","s":"H1004"},{"w":"of the LORD;","s":"H3068"},{"w":"the priests","s":"H3548"},{"w":"are in mourning,","s":"H0056"},{"w":"those who minister","s":"H8334"},{"w":"before the LORD.","s":"H3068"}],"10":[{"w":"The field","s":"H7704"},{"w":"is ruined;","s":"H7703"},{"w":"the land","s":"H0127"},{"w":"mourns.","s":"H0056"},{"w":"For","s":"H3588"},{"w":"the grain","s":"H1715"},{"w":"is destroyed,","s":"H7703"},{"w":"the new wine","s":"H8492"},{"w":"is dried up,","s":"H3001"},{"w":"[and] the oil fails.","s":"H3323"}],"11":[{"w":"Be dismayed,","s":"H0954"},{"w":"O farmers,","s":"H0406"},{"w":"wail,","s":"H3213"},{"w":"O vinedressers,","s":"H3755"},{"w":"over","s":"H5921"},{"w":"the wheat","s":"H2406"},{"w":"and","s":"H5921"},{"w":"barley,","s":"H8184"},{"w":"because","s":"H3588"},{"w":"the harvest","s":"H7105"},{"w":"of the field","s":"H7704"},{"w":"has perished.","s":"H0006"}],"12":[{"w":"The grapevine","s":"H1612"},{"w":"is dried up,","s":"H3001"},{"w":"and the fig tree","s":"H8384"},{"w":"is withered;","s":"H0535"},{"w":"the pomegranate,","s":"H7416"},{"w":"palm,","s":"H8558"},{"w":"and apple—","s":"H8598"},{"w":"all","s":"H3605"},{"w":"the trees","s":"H6086"},{"w":"of the orchard—","s":"H7704"},{"w":"are withered.","s":"H3001"},{"w":"Surely","s":"H3588"},{"w":"the joy","s":"H8342"},{"w":"of","s":"H4480"},{"w":"vvv","s":"H1121"},{"w":"mankind","s":"H0120"},{"w":"has dried up.","s":"H0954"}],"13":[{"w":"Put on [sackcloth]","s":"H2296"},{"w":"and lament,","s":"H5594"},{"w":"O priests;","s":"H3548"},{"w":"wail,","s":"H3213"},{"w":"O ministers","s":"H8334"},{"w":"of the altar.","s":"H4196"},{"w":"Come,","s":"H0935"},{"w":"spend the night","s":"H3885"},{"w":"in sackcloth,","s":"H8242"},{"w":"O ministers","s":"H8334"},{"w":"of my God,","s":"H0430"},{"w":"because","s":"H3588"},{"w":"the grain","s":"H4503"},{"w":"and drink offerings","s":"H5262"},{"w":"are withheld","s":"H4513"},{"w":"from the house","s":"H1004"},{"w":"of your God.","s":"H0430"}],"14":[{"w":"Consecrate","s":"H6942"},{"w":"a fast;","s":"H6685"},{"w":"proclaim","s":"H7121"},{"w":"a solemn assembly!","s":"H6116"},{"w":"Gather","s":"H0622"},{"w":"the elders","s":"H2205"},{"w":"and all","s":"H3605"},{"w":"the residents","s":"H3427"},{"w":"of the land","s":"H0776"},{"w":"to the house","s":"H1004"},{"w":"of the LORD","s":"H3068"},{"w":"your God,","s":"H0430"},{"w":"and cry out","s":"H2199"},{"w":"to","s":"H0413"},{"w":"the LORD.","s":"H3068"}],"15":[{"w":"Alas","s":"H0162"},{"w":"for the day!","s":"H3117"},{"w":"For","s":"H3588"},{"w":"the Day","s":"H3117"},{"w":"of the LORD","s":"H3068"},{"w":"is near,","s":"H7138"},{"w":"and it will come","s":"H0935"},{"w":"as destruction","s":"H7701"},{"w":"from the Almighty.","s":"H7706"}],"16":[{"w":"Has not","s":"H3808"},{"w":"the food","s":"H0400"},{"w":"been cut off","s":"H3772"},{"w":"before","s":"H5048"},{"w":"our very eyes—","s":"H5869"},{"w":"joy","s":"H8057"},{"w":"and gladness","s":"H1524"},{"w":"from the house","s":"H1004"},{"w":"of our God?","s":"H0430"}],"17":[{"w":"The seeds","s":"H6507"},{"w":"lie shriveled","s":"H5685"},{"w":"beneath","s":"H8478"},{"w":"the clods;","s":"H4053"},{"w":"the storehouses","s":"H0214"},{"w":"are in ruins;","s":"H8074"},{"w":"the granaries","s":"H4460"},{"w":"are broken down,","s":"H2040"},{"w":"for","s":"H3588"},{"w":"the grain","s":"H1715"},{"w":"has withered away.","s":"H3001"}],"18":[{"w":"How","s":"H4100"},{"w":"the cattle","s":"H0929"},{"w":"groan!","s":"H0584"},{"w":"The herds","s":"H5739"},{"w":"wander in confusion","s":"H0943"},{"w":"because","s":"H3588"},{"w":"they have no","s":"H0369"},{"w":"pasture","s":"H4829"},{"w":"Even","s":"H1571"},{"w":"the flocks","s":"H5739"},{"w":"of sheep","s":"H6629"},{"w":"are suffering.","s":"H0816"}],"19":[{"w":"To You,","s":"H0413"},{"w":"O LORD,","s":"H3068"},{"w":"I call,","s":"H7121"},{"w":"for","s":"H3588"},{"w":"fire","s":"H0784"},{"w":"has consumed","s":"H0398"},{"w":"the open","s":"H4057"},{"w":"pastures","s":"H4999"},{"w":"and flames","s":"H3852"},{"w":"have scorched","s":"H3857"},{"w":"all","s":"H3605"},{"w":"the trees","s":"H6086"},{"w":"of the field.","s":"H7704"}],"20":[{"w":"Even","s":"H1571"},{"w":"the beasts","s":"H0929"},{"w":"of the field","s":"H7704"},{"w":"pant","s":"H6165"},{"w":"for You,","s":"H0413"},{"w":"for","s":"H3588"},{"w":"the streams","s":"H0650"},{"w":"of water","s":"H4325"},{"w":"have dried up,","s":"H3001"},{"w":"and fire","s":"H0784"},{"w":"has consumed","s":"H0398"},{"w":"the open","s":"H4057"},{"w":"pastures.","s":"H4999"}]}}