{"ref":"Isaiah 51","verses":{"1":[{"w":"Listen","s":"H8085"},{"w":"to Me","s":"H0413"},{"w":"you who pursue","s":"H7291"},{"w":"righteousness","s":"H6664"},{"w":"you who seek","s":"H1245"},{"w":"the LORD","s":"H3068"},{"w":"Look","s":"H5027"},{"w":"to","s":"H0413"},{"w":"the rock","s":"H6697"},{"w":"from which you were cut","s":"H2672"},{"w":"and to","s":"H0413"},{"w":"the quarry","s":"H4718"},{"w":"from which you were hewn","s":"H5365"}],"2":[{"w":"Look","s":"H5027"},{"w":"to","s":"H0413"},{"w":"Abraham","s":"H0085"},{"w":"your father","s":"H0001"},{"w":"and to","s":"H0413"},{"w":"Sarah","s":"H8283"},{"w":"who gave you birth","s":"H2342"},{"w":"When","s":"H3588"},{"w":"I called him","s":"H7121"},{"w":"he was but one","s":"H0259"},{"w":"then I blessed him","s":"H1288"},{"w":"and multiplied him","s":"H7235"}],"3":[{"w":"For","s":"H3588"},{"w":"the LORD","s":"H3068"},{"w":"will comfort","s":"H5162"},{"w":"Zion","s":"H6726"},{"w":"and will look with compassion","s":"H5162"},{"w":"on all her","s":"H3605"},{"w":"ruins","s":"H2723"},{"w":"He will make","s":"H7760"},{"w":"her wilderness","s":"H4057"},{"w":"like Eden","s":"H5731"},{"w":"and her desert","s":"H6160"},{"w":"like the garden","s":"H1588"},{"w":"of the LORD","s":"H3068"},{"w":"Joy","s":"H8342"},{"w":"and gladness","s":"H8057"},{"w":"will be found","s":"H4672"},{"w":"in her","s":""},{"w":"thanksgiving","s":"H8426"},{"w":"and melodious","s":"H2172"},{"w":"song","s":"H6963"}],"4":[{"w":"Pay attention","s":"H7181"},{"w":"to Me","s":"H0413"},{"w":"My people","s":"H5971"},{"w":"and listen","s":"H0238"},{"w":"to Me","s":"H0413"},{"w":"My nation","s":"H3816"},{"w":"for","s":"H3588"},{"w":"a law","s":"H8451"},{"w":"will go out from Me","s":"H3318"},{"w":"and My justice [will become]","s":"H4941"},{"w":"a light","s":"H0216"},{"w":"to the nations","s":"H5971"},{"w":"I will bring it about quickly","s":"H7280"}],"5":[{"w":"My righteousness","s":"H6664"},{"w":"draws near","s":"H7138"},{"w":"My salvation","s":"H3468"},{"w":"is on the way","s":"H3318"},{"w":"and My arms","s":"H2220"},{"w":"will bring justice","s":"H8199"},{"w":"to the nations","s":"H5971"},{"w":"The islands","s":"H0339"},{"w":"will look","s":"H6960"},{"w":"for Me","s":"H0413"},{"w":"and wait in hope","s":"H3176"},{"w":"for","s":"H0413"},{"w":"My arm","s":"H2220"}],"6":[{"w":"Lift up","s":"H5375"},{"w":"your eyes","s":"H5869"},{"w":"to the heavens","s":"H8064"},{"w":"and look","s":"H5027"},{"w":"at","s":"H0413"},{"w":"the earth","s":"H0776"},{"w":"below","s":"H8478"},{"w":"for","s":"H3588"},{"w":"the heavens","s":"H8064"},{"w":"will vanish","s":"H4414"},{"w":"like smoke","s":"H6227"},{"w":"the earth","s":"H0776"},{"w":"will wear out","s":"H1086"},{"w":"like a garment","s":"H0899"},{"w":"and its people","s":"H3427"},{"w":"will die","s":"H4191"},{"w":"like [gnats]","s":"H3644"},{"w":"But My salvation","s":"H3444"},{"w":"will last forever","s":"H1961"},{"w":"and My righteousness","s":"H6666"},{"w":"will never","s":"H3808"},{"w":"fail","s":"H2865"}],"7":[{"w":"Listen","s":"H8085"},{"w":"to Me","s":"H0413"},{"w":"you who know","s":"H3045"},{"w":"what is right","s":"H6664"},{"w":"you people","s":"H5971"},{"w":"with My law","s":"H8451"},{"w":"in your hearts","s":"H3820"},{"w":"Do not","s":"H0408"},{"w":"fear","s":"H3372"},{"w":"the scorn","s":"H2781"},{"w":"of men","s":"H0582"},{"w":"do not","s":"H0408"},{"w":"be broken","s":"H2865"},{"w":"by their insults","s":"H1421"}],"8":[{"w":"For","s":"H3588"},{"w":"the moth","s":"H6211"},{"w":"will devour them","s":"H0398"},{"w":"like a garment","s":"H0899"},{"w":"and the worm","s":"H5580"},{"w":"will eat them","s":"H0398"},{"w":"like wool","s":"H6785"},{"w":"But My righteousness","s":"H6666"},{"w":"will last forever","s":"H1961"},{"w":"My salvation","s":"H3444"},{"w":"through all generations","s":"H1755"}],"9":[{"w":"Awake","s":"H5782"},{"w":"awake","s":"H5782"},{"w":"put on","s":"H3847"},{"w":"strength","s":"H5797"},{"w":"O arm","s":"H2220"},{"w":"of the LORD","s":"H3068"},{"w":"Wake up","s":"H5782"},{"w":"as in days","s":"H3117"},{"w":"past","s":"H6924"},{"w":"as in generations","s":"H1755"},{"w":"of old","s":"H5769"},{"w":"Was it not","s":"H3808"},{"w":"You","s":"H0859"},{"w":"who cut Rahab","s":"H7294"},{"w":"to pieces","s":"H2672"},{"w":"who pierced through","s":"H2490"},{"w":"the dragon","s":"H8577"}],"10":[{"w":"Was it not","s":"H3808"},{"w":"You","s":"H0859"},{"w":"who dried up","s":"H2717"},{"w":"the sea","s":"H3220"},{"w":"the waters","s":"H4325"},{"w":"of the great","s":"H7227"},{"w":"deep","s":"H8415"},{"w":"who made","s":"H7760"},{"w":"a road","s":"H1870"},{"w":"in the depths","s":"H4615"},{"w":"of the sea","s":"H3220"},{"w":"for the redeemed","s":"H1350"},{"w":"to cross over","s":"H5674"}],"11":[{"w":"So the redeemed","s":"H6299"},{"w":"of the LORD","s":"H3068"},{"w":"will return","s":"H7725"},{"w":"and enter","s":"H0935"},{"w":"Zion","s":"H6726"},{"w":"with singing","s":"H7440"},{"w":"crowned","s":"H5921"},{"w":"with everlasting","s":"H5769"},{"w":"joy","s":"H8057"},{"w":"Gladness","s":"H8342"},{"w":"and joy","s":"H8057"},{"w":"will overtake them","s":"H5381"},{"w":"and sorrow","s":"H3015"},{"w":"and sighing","s":"H0585"},{"w":"will flee","s":"H5127"}],"12":[{"w":"I","s":"H0595"},{"w":"even I","s":"H0595"},{"w":"am He","s":"H1931"},{"w":"who comforts you","s":"H5162"},{"w":"Why","s":"H4310"},{"w":"should you","s":"H0859"},{"w":"be afraid","s":"H3372"},{"w":"of mortal","s":"H4191"},{"w":"man","s":"H0582"},{"w":"of a son","s":"H1121"},{"w":"of man","s":"H0120"},{"w":"who withers","s":"H5414"},{"w":"like grass","s":"H2682"}],"13":[{"w":"But you have forgotten","s":"H7911"},{"w":"the LORD","s":"H3068"},{"w":"your Maker","s":"H6213"},{"w":"who stretched out","s":"H5186"},{"w":"the heavens","s":"H8064"},{"w":"and laid the foundations","s":"H3245"},{"w":"of the earth","s":"H0776"},{"w":"You live in terror","s":"H6342"},{"w":"vvv","s":"H8548"},{"w":"all day long","s":"H3605"},{"w":"because of","s":"H6440"},{"w":"the fury","s":"H2534"},{"w":"of the oppressor","s":"H6693"},{"w":"who","s":"H0834"},{"w":"is bent","s":"H3559"},{"w":"on destruction","s":"H7843"},{"w":"But where","s":"H0346"},{"w":"is the fury","s":"H2534"},{"w":"of the oppressor","s":"H6693"}],"14":[{"w":"The captive","s":"H6808"},{"w":"will soon","s":"H4116"},{"w":"be freed","s":"H6605"},{"w":"he will not","s":"H3808"},{"w":"die","s":"H4191"},{"w":"in the dungeon","s":"H7845"},{"w":"and his bread","s":"H3899"},{"w":"will not","s":"H3808"},{"w":"be lacking","s":"H2637"}],"15":[{"w":"For I","s":"H0595"},{"w":"am the LORD","s":"H3068"},{"w":"your God","s":"H0430"},{"w":"who stirs up","s":"H7280"},{"w":"the sea","s":"H3220"},{"w":"so that its waves","s":"H1530"},{"w":"roar","s":"H1993"},{"w":"the LORD","s":"H3068"},{"w":"of Hosts","s":"H6635"},{"w":"[is] His name","s":"H8034"}],"16":[{"w":"I have put","s":"H7760"},{"w":"My words","s":"H1697"},{"w":"in your mouth","s":"H6310"},{"w":"and covered you","s":"H3680"},{"w":"with the shadow","s":"H6738"},{"w":"of My hand","s":"H3027"},{"w":"to establish","s":"H5193"},{"w":"the heavens","s":"H8064"},{"w":"to found","s":"H3245"},{"w":"the earth","s":"H0776"},{"w":"and to say","s":"H0559"},{"w":"to Zion","s":"H6726"},{"w":"You","s":"H0859"},{"w":"are My people","s":"H5971"}],"17":[{"w":"Awake","s":"H5782"},{"w":"awake","s":"H5782"},{"w":"Rise up","s":"H6965"},{"w":"O Jerusalem","s":"H3389"},{"w":"you who","s":"H0834"},{"w":"have drunk","s":"H8354"},{"w":"from the hand","s":"H3027"},{"w":"of the LORD","s":"H3068"},{"w":"the cup","s":"H3563"},{"w":"of His fury","s":"H2534"},{"w":"you who have drained","s":"H8354"},{"w":"the goblet","s":"H6907"},{"w":"to the dregs","s":"H4680"},{"w":"the cup","s":"H3563"},{"w":"that makes men stagger","s":"H8653"}],"18":[{"w":"Among all","s":"H3605"},{"w":"the sons","s":"H1121"},{"w":"she bore","s":"H3205"},{"w":"there is no","s":"H0369"},{"w":"one to guide","s":"H5095"},{"w":"her","s":""},{"w":"among all","s":"H3605"},{"w":"the sons","s":"H1121"},{"w":"she brought up","s":"H1431"},{"w":"there is no","s":"H0369"},{"w":"one to take","s":"H2388"},{"w":"her hand","s":"H3027"}],"19":[{"w":"These","s":"H2007"},{"w":"pairs","s":"H8147"},{"w":"have befallen","s":"H7122"},{"w":"you","s":""},{"w":"devastation","s":"H7701"},{"w":"and destruction","s":"H7667"},{"w":"famine","s":"H7458"},{"w":"and sword","s":"H2719"},{"w":"Who","s":"H4310"},{"w":"will grieve for you","s":"H5110"},{"w":"Who","s":"H4310"},{"w":"can comfort you","s":"H5162"}],"20":[{"w":"Your sons","s":"H1121"},{"w":"have fainted","s":"H5968"},{"w":"they lie","s":"H7901"},{"w":"at the head","s":"H7218"},{"w":"of every","s":"H3605"},{"w":"street","s":"H2351"},{"w":"like an antelope","s":"H8377"},{"w":"in a net","s":"H4364"},{"w":"They are full","s":"H4392"},{"w":"of the wrath","s":"H2534"},{"w":"of the LORD","s":"H3068"},{"w":"the rebuke","s":"H1606"},{"w":"of your God","s":"H0430"}],"21":[{"w":"Therefore","s":"H3651"},{"w":"now","s":"H4994"},{"w":"hear","s":"H8085"},{"w":"this","s":"H2063"},{"w":"you afflicted one","s":"H6041"},{"w":"drunken","s":"H7937"},{"w":"but not","s":"H3808"},{"w":"with wine","s":"H3196"}],"22":[{"w":"Thus","s":"H3541"},{"w":"says","s":"H0559"},{"w":"your Lord","s":"H0113"},{"w":"the LORD","s":"H3068"},{"w":"even your God","s":"H0430"},{"w":"who defends","s":"H7378"},{"w":"His people","s":"H5971"},{"w":"See","s":"H2009"},{"w":"I have removed","s":"H3947"},{"w":"from your hand","s":"H3027"},{"w":"the cup","s":"H3563"},{"w":"of staggering","s":"H8653"},{"w":"From that goblet","s":"H6907"},{"w":"the cup","s":"H3563"},{"w":"of My fury","s":"H2534"},{"w":"you will never","s":"H3808"},{"w":"drink","s":"H8354"},{"w":"again","s":"H3254"}],"23":[{"w":"I will place it","s":"H7760"},{"w":"in the hands","s":"H3027"},{"w":"of your tormentors","s":"H3013"},{"w":"who","s":"H0834"},{"w":"told","s":"H0559"},{"w":"you","s":"H5315"},{"w":"Lie down","s":"H7812"},{"w":"so we can walk over you","s":"H5674"},{"w":"so that you made","s":"H7760"},{"w":"your back","s":"H1460"},{"w":"like the ground","s":"H0776"},{"w":"like a street","s":"H2351"},{"w":"to be traversed","s":"H5674"}]}}